korpuskulum/__init__.py
korpuskulum/config.py
korpuskulum/evaluate.py
korpuskulum/io.py
korpuskulum/main.py
korpuskulum/objects.py
korpuskulum/plotting.py
korpuskulum/prog_bar.py
korpuskulum-0.1.1.dist-info/LICENSE
korpuskulum-0.1.1.dist-info/METADATA
korpuskulum-0.1.1.dist-info/WHEEL
korpuskulum-0.1.1.dist-info/entry_points.txt
korpuskulum-0.1.1.dist-info/RECORD
