Metadata-Version: 2.3
Name: korpuskulum
Version: 0.1.1
Summary: Package to evaluate particle distribution with respect to segmented membranes
License: Apache License V.3
Author: Neville B.-y. Yee
Requires-Python: >=3.10
Classifier: License :: Other/Proprietary License
Classifier: Programming Language :: Python :: 3
Classifier: Programming Language :: Python :: 3.10
Classifier: Programming Language :: Python :: 3.11
Classifier: Programming Language :: Python :: 3.12
Classifier: Programming Language :: Python :: 3.13
Requires-Dist: icecream
Requires-Dist: matplotlib
Requires-Dist: numpy
Requires-Dist: pandas
Requires-Dist: rich
Requires-Dist: scikit-learn
Requires-Dist: scipy
Requires-Dist: starfile
Requires-Dist: tifffile
Requires-Dist: tqdm
Requires-Dist: typer
